{
    "name": "All Requests",
    "numberOfRequests": {
        "total": 107886,
        "ok": 101632,
        "ko": 6254
    },
    "minResponseTime": {
        "total": 0,
        "ok": 0,
        "ko": 309
    },
    "maxResponseTime": {
        "total": 64478,
        "ok": 60935,
        "ko": 64478
    },
    "meanResponseTime": {
        "total": 12126,
        "ok": 9417,
        "ko": 56158
    },
    "standardDeviation": {
        "total": 17929,
        "ok": 14369,
        "ko": 11478
    },
    "percentiles1": {
        "total": 2627,
        "ok": 2040,
        "ko": 60001
    },
    "percentiles2": {
        "total": 15944,
        "ok": 12206,
        "ko": 60009
    },
    "percentiles3": {
        "total": 59942,
        "ok": 43362,
        "ko": 61919
    },
    "percentiles4": {
        "total": 60448,
        "ok": 54322,
        "ko": 63022
    },
    "group1": {
    "name": "t < 800 ms",
    "htmlName": "t < 800 ms",
    "count": 38874,
    "percentage": 36
},
    "group2": {
    "name": "800 ms <= t < 1200 ms",
    "htmlName": "t >= 800 ms <br> t < 1200 ms",
    "count": 2313,
    "percentage": 2
},
    "group3": {
    "name": "t >= 1200 ms",
    "htmlName": "t >= 1200 ms",
    "count": 60445,
    "percentage": 56
},
    "group4": {
    "name": "failed",
    "htmlName": "failed",
    "count": 6254,
    "percentage": 6
},
    "meanNumberOfRequestsPerSecond": {
        "total": 404.0674157303371,
        "ok": 380.6441947565543,
        "ko": 23.423220973782772
    }
}